README.rst
setup.cfg
setup.py
plex_scrobble/__init__.py
plex_scrobble/__main__.py
plex_scrobble/plex_monitor.py
plex_scrobble/scrobble_cache.py
plex_scrobble.egg-info/PKG-INFO
plex_scrobble.egg-info/SOURCES.txt
plex_scrobble.egg-info/dependency_links.txt
plex_scrobble.egg-info/entry_points.txt
plex_scrobble.egg-info/requires.txt
plex_scrobble.egg-info/top_level.txt