Metadata-Version: 1.1
Name: plex-scrobble
Version: 4.1.1
Summary: Scrobble audio tracks played via Plex Media Center
Home-page: https://github.com/jesseward/plex-lastfm-scrobbler
Author: Jesse Ward
Author-email: jesse@jesseward.com
License: MIT
Platform: UNKNOWN
Classifier: Environment :: Console
Classifier: Development Status :: 5 - Production/Stable
Classifier: Programming Language :: Python :: 2.7
Classifier: Programming Language :: Python :: 3.5
Classifier: License :: OSI Approved :: MIT License
Classifier: Operating System :: OS Independent
